{"Energy":[{"symbol":"CL=F","name":"WTI Crude Oil","unit":"$/bbl","price":102.22000122070312,"change":-3.2399978637695312,"pct":-3.0722528844081607},{"symbol":"BZ=F","name":"Brent Crude","unit":"$/bbl","price":108.4800033569336,"change":-2.8899993896484375,"pct":-2.594953145708827},{"symbol":"NG=F","name":"Natural Gas","unit":"$/MMBtu","price":2.7850000858306885,"change":0.0010001659393310547,"pct":0.03592550172810655},{"symbol":"HO=F","name":"Heating Oil","unit":"$/gal","price":3.9514999389648438,"change":-0.1480998992919922,"pct":-3.61254525161082},{"symbol":"RB=F","name":"RBOB Gasoline","unit":"$/gal","price":3.603300094604492,"change":-0.04049992561340332,"pct":-1.1114749818509926}],"Metals":[{"symbol":"GC=F","name":"Gold","unit":"$/oz","price":4636.0,"change":-2.60009765625,"pct":-0.05605349893308875},{"symbol":"SI=F","name":"Silver","unit":"$/oz","price":76.33499908447266,"change":1.5349960327148438,"pct":2.0521336498511964},{"symbol":"HG=F","name":"Copper","unit":"$/lb","price":5.968999862670898,"change":-0.04550027847290039,"pct":-0.7565097249170144},{"symbol":"PL=F","name":"Platinum","unit":"$/oz","price":2001.300048828125,"change":8.9000244140625,"pct":0.446698670197009},{"symbol":"PA=F","name":"Palladium","unit":"$/oz","price":1542.5,"change":2.5,"pct":0.16233766233766234}],"Grains":[{"symbol":"ZW=F","name":"Wheat","unit":"\u00a2/bu","price":636.5,"change":-6.25,"pct":-0.9723842862699339},{"symbol":"ZC=F","name":"Corn","unit":"\u00a2/bu","price":479.5,"change":1.75,"pct":0.3663003663003663},{"symbol":"ZS=F","name":"Soybeans","unit":"\u00a2/bu","price":1201.5,"change":-1.25,"pct":-0.10392849719393059}],"Softs":[{"symbol":"CC=F","name":"Cocoa","unit":"$/ton","price":3598.0,"change":-35.0,"pct":-0.9633911368015413},{"symbol":"KC=F","name":"Coffee","unit":"\u00a2/lb","price":289.95001220703125,"change":4.25,"pct":1.4875743151597265},{"symbol":"CT=F","name":"Cotton","unit":"\u00a2/lb","price":83.0,"change":0.839996337890625,"pct":1.02239082333198},{"symbol":"SB=F","name":"Sugar #11","unit":"\u00a2/lb","price":14.970000267028809,"change":0.3600006103515625,"pct":2.4640699439512344}],"Livestock":[{"symbol":"LE=F","name":"Live Cattle","unit":"\u00a2/lb","price":253.0,"change":-1.024993896484375,"pct":-0.4035011991387201},{"symbol":"GF=F","name":"Feeder Cattle","unit":"\u00a2/lb","price":372.0249938964844,"change":-1.57501220703125,"pct":-0.4215771363223297},{"symbol":"HE=F","name":"Lean Hogs","unit":"\u00a2/lb","price":101.32499694824219,"change":-0.875,"pct":-0.8561644091272644}],"Crypto":[{"symbol":"BTC-USD","name":"Bitcoin","unit":"USD","price":78541.8828125,"change":2245.15625,"pct":2.9426639269521413},{"symbol":"ETH-USD","name":"Ethereum","unit":"USD","price":2307.39990234375,"change":50.599853515625,"pct":2.2421061866734577}]}